demeter/__init__.py
demeter/core.py
demeter/daemon.py
demeter/db.py
demeter/modbus.py
demeter/model.py
demeter/mqtt.py
demeter/service.py
demeter/tcp.py
demeter/web.py
demeter/admin/__init__.py
demeter/admin/model/__init__.py
demeter/admin/model/__load__.py
demeter/admin/model/manage_admin.py
demeter/admin/model/manage_log.py
demeter/admin/model/manage_role.py
demeter/admin/page/__init__.py
demeter/admin/page/__load__.py
demeter/admin/page/admin.py
demeter/admin/page/main.py
demeter/admin/page/upload.py
demeter/admin/page/user.py
demeter/admin/static/favicon.ico
demeter/admin/static/css/x-admin.css
demeter/admin/static/images/banner.png
demeter/admin/static/images/icon.png
demeter/admin/static/images/logo.png
demeter/admin/static/js/echarts.common.min.js
demeter/admin/static/js/jquery.min.js
demeter/admin/static/js/main.js
demeter/admin/static/js/x-admin.js
demeter/admin/static/js/x-layui.js
demeter/admin/static/lib/bootstrap/css/bootstrap-theme.css
demeter/admin/static/lib/bootstrap/css/bootstrap-theme.css.map
demeter/admin/static/lib/bootstrap/css/bootstrap-theme.min.css
demeter/admin/static/lib/bootstrap/css/bootstrap.css
demeter/admin/static/lib/bootstrap/css/bootstrap.css.map
demeter/admin/static/lib/bootstrap/css/bootstrap.min.css
demeter/admin/static/lib/bootstrap/fonts/glyphicons-halflings-regular.eot
demeter/admin/static/lib/bootstrap/fonts/glyphicons-halflings-regular.svg
demeter/admin/static/lib/bootstrap/fonts/glyphicons-halflings-regular.ttf
demeter/admin/static/lib/bootstrap/fonts/glyphicons-halflings-regular.woff
demeter/admin/static/lib/bootstrap/js/bootstrap.js
demeter/admin/static/lib/bootstrap/js/bootstrap.min.js
demeter/admin/static/lib/bootstrap/js/npm.js
demeter/admin/static/lib/layui/layui.js
demeter/admin/static/lib/layui/css/layui.css
demeter/admin/static/lib/layui/css/modules/code.css
demeter/admin/static/lib/layui/css/modules/laydate/icon.png
demeter/admin/static/lib/layui/css/modules/laydate/laydate.css
demeter_lib-1.0.7.dist-info/licenses/LICENSE
demeter_lib-1.0.7.dist-info/METADATA
demeter_lib-1.0.7.dist-info/WHEEL
demeter_lib-1.0.7.dist-info/top_level.txt
demeter_lib-1.0.7.dist-info/RECORD
