Metadata-Version: 2.4
Name: demeter_lib
Version: 1.0.7
Summary: A simple framework based on Tornado
Home-page: https://github.com/shemic/demeter
Author: Rabin
Author-email: 2934170@qq.com
License: MIT License
Classifier: Development Status :: 5 - Production/Stable
Classifier: Intended Audience :: Developers
Classifier: License :: OSI Approved :: MIT License
Classifier: Natural Language :: English
Classifier: Operating System :: OS Independent
Classifier: Programming Language :: Python :: 2
Classifier: Programming Language :: Python :: 3
Classifier: Topic :: Software Development :: Libraries :: Application Frameworks
License-File: LICENSE
Requires-Dist: tornado
Requires-Dist: pymysql
Requires-Dist: celery
Requires-Dist: short_url
Requires-Dist: requests
Requires-Dist: watchdog
Requires-Dist: asyncio
Dynamic: author
Dynamic: author-email
Dynamic: classifier
Dynamic: description
Dynamic: home-page
Dynamic: license
Dynamic: license-file
Dynamic: requires-dist
Dynamic: summary
